fftl/__init__.py
fftl-2025.1.1.dist-info/METADATA
fftl-2025.1.1.dist-info/WHEEL
fftl-2025.1.1.dist-info/licenses/LICENSE
fftl-2025.1.1.dist-info/RECORD
