Metadata-Version: 2.4
Name: fftl
Version: 2025.1.1
Summary: Generalised FFTLog for integral transforms
Project-URL: Documentation, https://fftl.readthedocs.io
Project-URL: Repository, https://github.com/ntessore/fftl
Project-URL: Issues, https://github.com/ntessore/fftl/issues
Author-email: Nicolas Tessore <n.tessore@ucl.ac.uk>
License-Expression: MIT
License-File: LICENSE
Keywords: FFTLog,Hankel transform,Laplace transform,Stieltjes transform,integral transform
Classifier: License :: OSI Approved :: MIT License
Requires-Python: >=3.8
Requires-Dist: numpy
Requires-Dist: scipy
Provides-Extra: docs
Requires-Dist: furo; extra == 'docs'
Requires-Dist: jax; extra == 'docs'
Requires-Dist: matplotlib; extra == 'docs'
Requires-Dist: numpydoc; extra == 'docs'
Requires-Dist: sphinx; extra == 'docs'
Provides-Extra: test
Requires-Dist: jax; extra == 'test'
Requires-Dist: matplotlib; extra == 'test'
Requires-Dist: pytest; extra == 'test'
